odoo/addons/l10n_it_ddt_delivery/README.rst
odoo/addons/l10n_it_ddt_delivery/__init__.py
odoo/addons/l10n_it_ddt_delivery/__manifest__.py
odoo/addons/l10n_it_ddt_delivery/i18n/it.po
odoo/addons/l10n_it_ddt_delivery/i18n/l10n_it_ddt_delivery.pot
odoo/addons/l10n_it_ddt_delivery/i18n/sl.po
odoo/addons/l10n_it_ddt_delivery/models/__init__.py
odoo/addons/l10n_it_ddt_delivery/models/sale_order.py
odoo/addons/l10n_it_ddt_delivery/readme/CONTRIBUTORS.rst
odoo/addons/l10n_it_ddt_delivery/readme/DESCRIPTION.rst
odoo/addons/l10n_it_ddt_delivery/static/description/icon.png
odoo/addons/l10n_it_ddt_delivery/static/description/index.html
odoo/addons/l10n_it_ddt_delivery/tests/__init__.py
odoo/addons/l10n_it_ddt_delivery/tests/test_ddt_delivery.py
odoo/addons/l10n_it_ddt_delivery/wizards/__init__.py
odoo/addons/l10n_it_ddt_delivery/wizards/ddt_from_pickings.py
odoo11_addon_l10n_it_ddt_delivery-11.0.1.0.0.99.dev4.dist-info/METADATA
odoo11_addon_l10n_it_ddt_delivery-11.0.1.0.0.99.dev4.dist-info/WHEEL
odoo11_addon_l10n_it_ddt_delivery-11.0.1.0.0.99.dev4.dist-info/top_level.txt
odoo11_addon_l10n_it_ddt_delivery-11.0.1.0.0.99.dev4.dist-info/RECORD
