Metadata-Version: 2.1
Name: odoo11-addon-l10n-it-ddt-delivery
Version: 11.0.1.0.0.99.dev4
Summary: Copy carrier from picking and from sale order
Home-page: https://github.com/OCA/l10n-italy/tree/11.0/l10n_it_ddt_delivery
Author: Agile Business Group, Odoo Community Association (OCA)
Author-email: support@odoo-community.org
License: AGPL-3
Platform: UNKNOWN
Classifier: Programming Language :: Python
Classifier: Framework :: Odoo
Classifier: Framework :: Odoo :: 11.0
Classifier: License :: OSI Approved :: GNU Affero General Public License v3
Classifier: Development Status :: 5 - Production/Stable
Requires-Python: >=2.7, !=3.0.*, !=3.1.*, !=3.2.*, !=3.3.*, !=3.4.*
Requires-Dist: odoo11-addon-delivery-carrier-partner
Requires-Dist: odoo11-addon-l10n-it-ddt
Requires-Dist: odoo <11.1dev,>=11.0a
